MANIFEST.in
README.md
setup.py
theano_word2vec.egg-info/PKG-INFO
theano_word2vec.egg-info/SOURCES.txt
theano_word2vec.egg-info/dependency_links.txt
theano_word2vec.egg-info/requires.txt
theano_word2vec.egg-info/top_level.txt
word2vec/__init__.py
word2vec/counter_sampler.py
word2vec/dataset_reader.py
word2vec/deprecated.py
word2vec/noise_contrast.py
word2vec/test.py
word2vec/theano_minibatcher.py
word2vec/token_map.py
word2vec/unigram_dictionary.py
word2vec/w2v.py