Metadata-Version: 1.1
Name: theano-word2vec
Version: 0.2.1
Summary: word2vec using Theano and Lasagne
Home-page: https://github.com/enewe101/word2vec
Author: Edward Newell
Author-email: edward.newell@gmail.com
License: MIT
Keywords: word2vec word embeddings deep learning nlp
Platform: UNKNOWN
Classifier: Development Status :: 3 - Alpha
Classifier: Intended Audience :: Developers
Classifier: Topic :: Software Development :: Build Tools
Classifier: License :: OSI Approved :: MIT License
Classifier: Programming Language :: Python :: 2.7
